LICENSE
MANIFEST.in
README.md
VERSION
requirements.txt
setup.py
contres/__init__.py
contres/config.py
contres/contres
contres.egg-info/PKG-INFO
contres.egg-info/SOURCES.txt
contres.egg-info/dependency_links.txt
contres.egg-info/not-zip-safe
contres.egg-info/requires.txt
contres.egg-info/top_level.txt
contres/cmd/__init__.py
contres/cmd/_util.py
contres/cmd/activation.py
contres/cmd/config.py
contres/cmd/git.py
contres/cmd/init.py