Metadata-Version: 2.1
Name: contres
Version: 0.1.1
Summary: Continuous research command line interaface
Home-page: UNKNOWN
Author: Mirko Mälicke
Author-email: mirko.maelicke@kit.edu
License: GPL v3
Platform: UNKNOWN
